LICENSE
MANIFEST.in
README.md
setup.py
cloudify/__init__.py
cloudify/agent_utils.py
cloudify/amqp_client.py
cloudify/cluster.py
cloudify/cluster_status.py
cloudify/conflict_handlers.py
cloudify/constants.py
cloudify/context.py
cloudify/cryptography_utils.py
cloudify/decorators.py
cloudify/deployment_dependencies.py
cloudify/dispatch.py
cloudify/endpoint.py
cloudify/error_handling.py
cloudify/event.py
cloudify/exceptions.py
cloudify/logs.py
cloudify/manager.py
cloudify/mocks.py
cloudify/models_states.py
cloudify/plugin_installer.py
cloudify/rabbitmq_client.py
cloudify/snapshots.py
cloudify/state.py
cloudify/systemddbus.py
cloudify/utils.py
cloudify/zip_utils.py
cloudify/compute/__init__.py
cloudify/ctx_wrappers/__init__.py
cloudify/ctx_wrappers/ctx-py.py
cloudify/plugins/__init__.py
cloudify/plugins/install_utils.py
cloudify/plugins/lifecycle.py
cloudify/plugins/workflows.py
cloudify/proxy/__init__.py
cloudify/proxy/client.py
cloudify/proxy/server.py
cloudify/snmp/CLOUDIFY-MIB.mib
cloudify/snmp/__init__.py
cloudify/snmp/snmp_trap.py
cloudify/test_utils/__init__.py
cloudify/test_utils/dispatch_helper.py
cloudify/test_utils/local_workflow_decorator.py
cloudify/test_utils/mock_rest_client.py
cloudify/workflows/__init__.py
cloudify/workflows/amqp_dispatcher.py
cloudify/workflows/events.py
cloudify/workflows/local.py
cloudify/workflows/tasks.py
cloudify/workflows/tasks_graph.py
cloudify/workflows/workflow_api.py
cloudify/workflows/workflow_context.py
cloudify_async_client/__init__.py
cloudify_async_client/audit_log.py
cloudify_async_client/client.py
cloudify_common.egg-info/PKG-INFO
cloudify_common.egg-info/SOURCES.txt
cloudify_common.egg-info/dependency_links.txt
cloudify_common.egg-info/entry_points.txt
cloudify_common.egg-info/not-zip-safe
cloudify_common.egg-info/requires.txt
cloudify_common.egg-info/top_level.txt
cloudify_rest_client/__init__.py
cloudify_rest_client/_datetime_compat.py
cloudify_rest_client/agents.py
cloudify_rest_client/audit_log.py
cloudify_rest_client/blueprints.py
cloudify_rest_client/bytes_stream_utils.py
cloudify_rest_client/client.py
cloudify_rest_client/cluster.py
cloudify_rest_client/community_contacts.py
cloudify_rest_client/constants.py
cloudify_rest_client/deployment_modifications.py
