Metadata-Version: 2.1
Name: cloudify-common
Version: 7.0.4
Summary: Cloudify Common
Author: Cloudify
Author-email: cosmo-admin@cloudify.co
License: LICENSE
Requires-Python: >=3.6
Provides-Extra: dispatcher
Provides-Extra: snmp
License-File: LICENSE
